bootstrap_select/__init__.py
bootstrap_select/apps.py
bootstrap_select/settings.py
bootstrap_select/widgets.py
bootstrap_select/static/bootstrap_select/bootstrap_select.css
django_bootstrap_select-0.1.3.dist-info/DESCRIPTION.rst
django_bootstrap_select-0.1.3.dist-info/METADATA
django_bootstrap_select-0.1.3.dist-info/RECORD
django_bootstrap_select-0.1.3.dist-info/WHEEL
django_bootstrap_select-0.1.3.dist-info/metadata.json
django_bootstrap_select-0.1.3.dist-info/top_level.txt
