Metadata-Version: 1.1
Name: django-bootstrap-select
Version: 0.1.3
Summary: A Django wrapper for the Bootstrap Select library
Home-page: https://github.com/voxy/django-bootstrap-select
Author: Joshua Massover
Author-email: joshua.massover@gmail.com
License: MIT
Keywords: django-bootstrap-select
Platform: UNKNOWN
Classifier: Development Status :: 3 - Alpha
Classifier: Framework :: Django
Classifier: Framework :: Django :: 1.8
Classifier: Framework :: Django :: 1.9
Classifier: Framework :: Django :: 1.10
Classifier: Framework :: Django :: 1.11
Classifier: Intended Audience :: Developers
Classifier: License :: OSI Approved :: BSD License
Classifier: Natural Language :: English
Classifier: Programming Language :: Python :: 2
Classifier: Programming Language :: Python :: 2.7
Classifier: Programming Language :: Python :: 3
Classifier: Programming Language :: Python :: 3.4
Classifier: Programming Language :: Python :: 3.5
